analysis/__init__.py
analysis/config.py
analysis/input_parser.py
analysis/main.py
analysis/annotate/__init__.py
analysis/annotate/annotateapp.py
analysis/annotate/annotateapp_builder.py
analysis/annotate/annotation.py
analysis/annotate/launcher.py
analysis/annotate/parser.py
analysis/annotate/report/__init__.py
analysis/annotate/report/annotate_tsv.py
analysis/annotate/report/pdf.py
analysis/annotate/report/rendering.py
analysis/annotate/report/composers/__init__.py
analysis/annotate/report/composers/composer.py
analysis/annotate/report/composers/first_page_composer.py
analysis/annotate/report/composers/mds_page_composer.py
analysis/annotate/report/composers/pie_page_composer.py
analysis/ari/__init__.py
analysis/ari/ariapp.py
analysis/ari/ariapp_builder.py
analysis/ari/breakdowns.py
analysis/ari/launcher.py
analysis/ari/parser.py
analysis/shared/__init__.py
analysis/shared/categories.py
analysis/shared/ihecjson.py
analysis/shared/matrix.py
analysis/shared/metadata.py
analysis/shared/clustering/__init__.py
analysis/shared/clustering/clusters.py
analysis/shared/clustering/hierarchical_clustering.py
analysis/shared/clustering/scipypatch.py
analysis/shared/exception/__init__.py
analysis/shared/exception/geecanalysiserror.py
analysis/shared/exception/geecanalysisexception.py
analysis/shared/util/__init__.py
analysis/shared/util/labels.py
analysis/shared/util/string_builder.py
analysis/slice/__init__.py
analysis/slice/launcher.py
analysis/slice/parser.py
analysis/slice/slice_cluster.py
analysis/slice/slice_filename.py
analysis/slice/slice_matrix.py
analysis/util/__init__.py
analysis/util/cat.py
analysis/util/grep.py
analysis/util/launcher.py
analysis/util/parser.py
tests/__init__.py
tests/context.py
tests/annotate/__init__.py
tests/annotate/test_annotateapp.py
tests/annotate/test_annotateapp_builder.py
tests/annotate/test_annotation.py
tests/annotate/test_parser.py
tests/annotate/report/__init__.py
tests/annotate/report/test_annotate_tsv.py
epigeec_analysis-1.2.3.dist-info/LICENSE
epigeec_analysis-1.2.3.dist-info/METADATA
epigeec_analysis-1.2.3.dist-info/WHEEL
epigeec_analysis-1.2.3.dist-info/entry_points.txt
epigeec_analysis-1.2.3.dist-info/top_level.txt
epigeec_analysis-1.2.3.dist-info/RECORD
