Metadata-Version: 2.1
Name: epigeec-analysis
Version: 1.2.3
Summary: Analysis tools for epiGeEC
Home-page: https://bitbucket.org/labjacquespe/epigeec_analysis
Author: Simon Hébert-Deschamps
Author-email: simon.hebert-deschamps@usherbrooke.ca
License: UNKNOWN
Platform: UNKNOWN
Classifier: Operating System :: OS Independent
Classifier: Programming Language :: Python
Classifier: License :: OSI Approved :: GNU General Public License v3 (GPLv3)
Classifier: Topic :: Scientific/Engineering :: Bio-Informatics
Classifier: Intended Audience :: Science/Research
Classifier: Environment :: Console
Requires-Python: >=2.7.5, !=3.0.*, !=3.1.*, !=3.2.*, !=3.3.*, !=3.4.*, <4
Requires-Dist: matplotlib
Requires-Dist: numpy
Requires-Dist: pandas
Requires-Dist: scipy
Requires-Dist: sklearn
Requires-Dist: reportlab
